setup.cfg
setup.py
lisa_plugins_wifiled/__init__.py
lisa_plugins_wifiled/models.py
lisa_plugins_wifiled/serializers.py
lisa_plugins_wifiled/urls.py
lisa_plugins_wifiled/views.py
lisa_plugins_wifiled.egg-info/PKG-INFO
lisa_plugins_wifiled.egg-info/SOURCES.txt
lisa_plugins_wifiled.egg-info/dependency_links.txt
lisa_plugins_wifiled.egg-info/entry_points.txt
lisa_plugins_wifiled.egg-info/not-zip-safe
lisa_plugins_wifiled.egg-info/pbr.json
lisa_plugins_wifiled.egg-info/requires.txt
lisa_plugins_wifiled.egg-info/top_level.txt
lisa_plugins_wifiled/locale/de/LC_MESSAGES/django.po
lisa_plugins_wifiled/locale/en/LC_MESSAGES/django.po
lisa_plugins_wifiled/locale/fr/LC_MESSAGES/django.po
lisa_plugins_wifiled/migrations/0001_initial.py
lisa_plugins_wifiled/migrations/0002_auto_20150626_1525.py
lisa_plugins_wifiled/migrations/0003_auto_20150626_1527.py
lisa_plugins_wifiled/migrations/__init__.py