Metadata-Version: 1.1
Name: lisa-plugins-wifiled
Version: 0.1.3
Summary: LISA Plugins Shopping
Home-page: https://github.com/project-lisa/lisa-plugins-wifiled
Author: Julien Syx
Author-email: julien@lisa-project.net
License: Apache
Platform: UNKNOWN
Classifier: Development Status :: 2 - Pre-Alpha
Classifier: Environment :: Web Environment
Classifier: Framework :: Django
Classifier: Intended Audience :: Developers
Classifier: License :: OSI Approved :: BSD License
Classifier: Operating System :: OS Independent
Classifier: Natural Language :: English
Classifier: Programming Language :: Python :: 2
Classifier: Programming Language :: Python :: 2.7
Classifier: Programming Language :: Python :: 3
Classifier: Programming Language :: Python :: 3.4
Classifier: Topic :: Internet :: WWW/HTTP
